pick_kernel/__init__.py
pick_kernel/__main__.py
pick_kernel/exceptions.py
pick_kernel/kernel.py
pick_kernel/kernelbase.py
pick_kernel/kernelspec.py
pick_kernel/subkernels.py
pick_kernel/version.py
pick_kernel/tests/__init__.py
pick_kernel/tests/test_subkernel.py
pick_kernel-0.0.4.dist-info/LICENSE
pick_kernel-0.0.4.dist-info/METADATA
pick_kernel-0.0.4.dist-info/WHEEL
pick_kernel-0.0.4.dist-info/entry_points.txt
pick_kernel-0.0.4.dist-info/top_level.txt
pick_kernel-0.0.4.dist-info/RECORD
