Metadata-Version: 2.1
Name: pick-kernel
Version: 0.0.4
Summary: The Jupyter Kernel for Choosy Users
Home-page: https://github.com/rgbkrk/pick
Author: Kyle Kelley
Author-email: rgbkrk@gmail.com
License: UNKNOWN
Platform: UNKNOWN
Classifier: Intended Audience :: Developers
Classifier: Intended Audience :: System Administrators
Classifier: Intended Audience :: Science/Research
Classifier: License :: OSI Approved :: BSD License
Classifier: Programming Language :: Python
Classifier: Programming Language :: Python :: 3
Classifier: Programming Language :: Python :: 3.6
Classifier: Programming Language :: Python :: 3.7
Classifier: Programming Language :: Python :: 3.8
Requires-Python: >=3.6
Requires-Dist: ipykernel (>=5.2.1)
Requires-Dist: jupyter-client (>=6.1.3)
Requires-Dist: tornado (>=4.2)
Requires-Dist: pyzmq (>=19.0.0)
Requires-Dist: entrypoints
Provides-Extra: all
Provides-Extra: dev
Requires-Dist: bump2version ; extra == 'dev'
Requires-Dist: papermill ; extra == 'dev'
Requires-Dist: pytest ; extra == 'dev'
Requires-Dist: pytest-asyncio ; extra == 'dev'
Requires-Dist: tox ; extra == 'dev'
Requires-Dist: mock ; extra == 'dev'
Provides-Extra: test
Requires-Dist: bump2version ; extra == 'test'
Requires-Dist: papermill ; extra == 'test'
Requires-Dist: pytest ; extra == 'test'
Requires-Dist: pytest-asyncio ; extra == 'test'
Requires-Dist: tox ; extra == 'test'
Requires-Dist: mock ; extra == 'test'
